<?xml version="1.0" encoding="UTF-8"?><Media xmlns:cdr="cips.nci.nih.gov/cdr">
 
 <MediaTitle>ovarian cancer stage IIIB - Spanish</MediaTitle>
 <PhysicalMedia>
  <ImageData>
   <ImageType>drawing</ImageType>
   <ImageEncoding>JPEG</ImageEncoding>
   <Color>Color</Color>
   <Labeled>Yes</Labeled>
   <LabelName language="es">Estadio IIIB</LabelName><LabelName language="es">Epiplón</LabelName><LabelName language="es">Trompa de Falopio</LabelName><LabelName language="es">Ganglios linfáticos</LabelName><LabelName language="es">Ovario</LabelName><LabelName language="es">Cáncer</LabelName><LabelName language="es">Útero</LabelName><LabelName language="es">Vejiga</LabelName><LabelName language="es">Peritoneo</LabelName><LabelName language="es">Colon</LabelName><LabelName language="es">Intestino delgado</LabelName><LabelName language="es">Tamaño del tumor</LabelName><LabelName language="es">2 cm o menos</LabelName><ImageDimensions><HeightPixels>2700</HeightPixels>
    
    
   <WidthPixels>3060</WidthPixels></ImageDimensions>
  </ImageData>
 </PhysicalMedia>
 <MediaSource>
  <DerivedFrom>
   <FromObject>
    <FromCdrMedia cdr:id="_1">
     <MediaID cdr:ref="CDR0000655351">ovarian cancer stage IIIB</MediaID>
    </FromCdrMedia>
   </FromObject><SourceFilename>OFPStage3BSpanish.jpeg</SourceFilename><Comment audience="Internal" date="2016-02-01" user="saucedol">Linked revised image</Comment><Comment audience="Internal" date="2010-01-15" user="dbuchhagen">Updated image, Spanish filename: OvarianCaStage3BSpanish3.jpg.</Comment>
   
  </DerivedFrom>
 </MediaSource>
 <MediaContent>
  <Categories>
   <Category>staging</Category>
  </Categories>
  <Diagnoses>
   
  <Diagnosis cdr:ref="CDR0000043701">ovarian epithelial cancer</Diagnosis><Diagnosis cdr:ref="CDR0000040968">fallopian tube cancer</Diagnosis><Diagnosis cdr:ref="CDR0000040969">primary peritoneal cavity cancer</Diagnosis></Diagnoses>
  
  <ContentDescriptions>
   <ContentDescription audience="Patients" language="es">La figura del estadio IIIB muestra cáncer en el interior de ambos ovarios que se diseminó al epiplón. El cáncer en el epiplón mide 2 cm o menos. En un recuadro, se muestra que 2 cm es aproximadamente el tamaño de un maní.   También se muestran el intestino delgado, el colon, las trompas de Falopio, el útero,   la vejiga y los ganglios linfáticos detrás del peritoneo. </ContentDescription>
  <ContentDescription audience="Health_professionals" language="es">La figura del estadio IIIB muestra cáncer en el interior de ambos ovarios que se diseminó al epiplón. El cáncer en el epiplón mide 2 cm o menos. En un recuadro, se muestra que 2 cm es aproximadamente el tamaño de un maní.   También se muestran el intestino delgado, el colon, las trompas de Falopio, el útero,   la vejiga y los ganglios linfáticos detrás del peritoneo.</ContentDescription></ContentDescriptions>
  <Captions>
   <MediaCaption audience="Patients" language="es">En el estadio IIIB, el cáncer se encuentra en uno o ambos ovarios o las trompas de Falopio y se diseminó hasta el epiplón, y el cáncer en el epiplón mide 2 cm o menos. El cáncer se puede haber diseminado a los ganglios linfáticos detrás del peritoneo.</MediaCaption>
  <MediaCaption audience="Health_professionals" language="es">En el estadio IIIB, el cáncer se encuentra en uno o ambos ovarios o las trompas de Falopio y se diseminó hasta el epiplón, y el cáncer en el epiplón mide 2 cm o menos. El cáncer se puede haber diseminado a los ganglios linfáticos detrás del peritoneo.</MediaCaption></Captions>
 </MediaContent>
 <ProposedUse>
  <Summary cdr:ref="CDR0000256785">Cáncer epitelial de ovario, de trompa de Falopio y primario de peritoneo: Tratamiento</Summary>
  <Glossary cdr:ref="CDR0000045901">stage III ovarian epithelial, fallopian tube, and primary peritoneal cancer</Glossary>
 </ProposedUse>
 <ProcessingStatuses><ProcessingStatus>
        <ProcessingStatusValue>Processing Complete</ProcessingStatusValue>
        <ProcessingStatusDate>2016-02-03</ProcessingStatusDate>
        <EnteredBy>saucedol</EnteredBy>
        
       </ProcessingStatus><ProcessingStatus>
        <ProcessingStatusValue>Translation complete</ProcessingStatusValue>
        <ProcessingStatusDate>2016-02-03</ProcessingStatusDate>
        <EnteredBy>saucedol</EnteredBy>
        
       </ProcessingStatus><ProcessingStatus>
        <ProcessingStatusValue>Spanish labels sent to artist</ProcessingStatusValue>
        <ProcessingStatusDate>2016-01-26</ProcessingStatusDate>
        <EnteredBy>saucedol</EnteredBy>
        <Comment>Revised labels sent to Terese</Comment>
       </ProcessingStatus><ProcessingStatus>
        <ProcessingStatusValue>Translation pending</ProcessingStatusValue>
        <ProcessingStatusDate>2016-01-22</ProcessingStatusDate>
        <EnteredBy>saucedol</EnteredBy>
        
       </ProcessingStatus><ProcessingStatus>
        <ProcessingStatusValue>Processing Complete</ProcessingStatusValue>
        <ProcessingStatusDate>2011-10-24</ProcessingStatusDate>
        <EnteredBy>lsaucedo</EnteredBy>
        <Comment>Linked revised image</Comment>
       </ProcessingStatus><ProcessingStatus>
        <ProcessingStatusValue>Translation complete</ProcessingStatusValue>
        <ProcessingStatusDate>2011-10-24</ProcessingStatusDate>
        <EnteredBy>lsaucedo</EnteredBy>
        <Comment>QCd labels, caption and content description</Comment>
       </ProcessingStatus><ProcessingStatus>
        <ProcessingStatusValue>Spanish labels sent to artist</ProcessingStatusValue>
        <ProcessingStatusDate>2011-10-11</ProcessingStatusDate>
        <EnteredBy>lsaucedo</EnteredBy>
        <Comment>Revised  labels sent to Terese, caption and content description QCd</Comment>
       </ProcessingStatus>
  <ProcessingStatus>
   <ProcessingStatusValue>Translation pending</ProcessingStatusValue>
   <ProcessingStatusDate>2009-11-05</ProcessingStatusDate>
   <EnteredBy>lsaucedo</EnteredBy>
   
  <Comment audience="Internal" date="2010-01-15" user="dbuchhagen">2010-01-15: Translation complete.</Comment></ProcessingStatus>
 </ProcessingStatuses>
</Media>
