<?xml version="1.0" encoding="UTF-8"?><Media xmlns:cdr="cips.nci.nih.gov/cdr" Usage="External">
 
 <MediaTitle>nonsteroidal anti-inflammatory drug-Spanish</MediaTitle>
  <PhysicalMedia>
    <SoundData>
      <SoundType>Speech</SoundType>
      <SoundEncoding>MP3</SoundEncoding>
      <RunSeconds>3</RunSeconds>
    </SoundData>
  </PhysicalMedia>
  <MediaSource>
    <OriginalSource>
      <Creator>Vanessa Richardson, VR Voice</Creator>
      <DateCreated>2013-04-24</DateCreated>
      <SourceFilename>44481_es.rrmp3</SourceFilename>
    </OriginalSource>
  </MediaSource>
  <MediaContent>
    <Categories>
      <Category>pronunciation</Category>
    </Categories>
    <ContentDescriptions>
      <ContentDescription audience="Patients" language="es">Pronunciation of dictionary term "medicamento antinflamatorio no esteroide"</ContentDescription>
    </ContentDescriptions><Comment audience="Internal" date="2013-04-24" user="lsaucedo">Made editorial change to term name and linked re-recorded audio</Comment>
  </MediaContent>
  <ProposedUse>
    <Glossary cdr:ref="CDR0000044481">nonsteroidal anti-inflammatory drug</Glossary>
  </ProposedUse>
</Media>
