<Media xmlns:cdr="cips.nci.nih.gov/cdr" Usage="External">
 
 <MediaTitle>autologous stem cell transplant</MediaTitle>
  <PhysicalMedia>
    <SoundData>
      <SoundType>Speech</SoundType>
      <SoundEncoding>MP3</SoundEncoding>
      <RunSeconds>4</RunSeconds>
    </SoundData>
  </PhysicalMedia>
  <MediaSource>
    <OriginalSource>
      <Creator>Vanessa Richardson, VR Voice</Creator>
      <DateCreated>2020-01-26</DateCreated>
      <SourceFilename>270733_en_rr.mp3</SourceFilename>
    </OriginalSource>
  </MediaSource>
  <MediaContent>
    <Categories>
      <Category>pronunciation</Category>
    </Categories>
    <ContentDescriptions>
      <ContentDescription audience="Patients" language="en">Pronunciation of dictionary term "autologous stem cell transplant"</ContentDescription>
    </ContentDescriptions>
  </MediaContent>
  <ProposedUse>
    <Glossary cdr:ref="CDR0000270733">autologous stem cell transplant</Glossary>
  </ProposedUse>
<ProcessingStatuses><ProcessingStatus>
        <ProcessingStatusValue>Processing Complete</ProcessingStatusValue>
        <ProcessingStatusDate>2020-01-27</ProcessingStatusDate>
        <EnteredBy>kuhlmanna</EnteredBy>
        
       </ProcessingStatus><ProcessingStatus>
        <ProcessingStatusValue>Audio re-recording approved</ProcessingStatusValue>
        <ProcessingStatusDate>2020-01-27</ProcessingStatusDate>
        <EnteredBy>kuhlmanna</EnteredBy>
        
       </ProcessingStatus>
       <ProcessingStatus>
        <ProcessingStatusValue>Audio re-recording pending</ProcessingStatusValue>
        <ProcessingStatusDate>2020-01-23</ProcessingStatusDate>
        <EnteredBy>kuhlmanna</EnteredBy>
        
       </ProcessingStatus></ProcessingStatuses></Media>