<Media xmlns:cdr="cips.nci.nih.gov/cdr" Usage="External">
 
 <MediaTitle>stage II nasal cavity and ethmoid sinus cancer-Spanish</MediaTitle>
  <PhysicalMedia>
    <SoundData>
      <SoundType>Speech</SoundType>
      <SoundEncoding>MP3</SoundEncoding>
      <RunSeconds>5</RunSeconds>
    </SoundData>
  </PhysicalMedia>
  <MediaSource>
    <OriginalSource>
      <Creator>Vanessa Richardson, VR Voice</Creator>
      <DateCreated>2020-04-01</DateCreated>
      <SourceFilename>450138_es_rr.mp3</SourceFilename>
    </OriginalSource>
  </MediaSource>
  <MediaContent>
    <Categories>
      <Category>pronunciation</Category>
    </Categories>
    <ContentDescriptions>
      <ContentDescription audience="Patients" language="es">Pronunciation of dictionary term "cáncer de cavidad nasal y seno paranasal  etmoidal en estadio II"</ContentDescription>
    </ContentDescriptions><Comment audience="Internal" date="2016-02-15" user="saucedol">Term revised and sent to Vanessa to re-record</Comment><Comment audience="Internal" date="2013-09-26" user="lsaucedo">Revised term and linked re-recorded audio</Comment>
  </MediaContent>
  <ProposedUse>
    <Glossary cdr:ref="CDR0000450138">stage II nasal cavity and ethmoid sinus cancer</Glossary>
  </ProposedUse>
<ProcessingStatuses><ProcessingStatus>
        <ProcessingStatusValue>Audio re-recording approved</ProcessingStatusValue>
        <ProcessingStatusDate>2020-04-01</ProcessingStatusDate>
        <EnteredBy>saucedol</EnteredBy>
        <Comment>Linked re-recorded audio</Comment>
       </ProcessingStatus><ProcessingStatus>
        <ProcessingStatusValue>Audio re-recording pending</ProcessingStatusValue>
        <ProcessingStatusDate>2019-10-17</ProcessingStatusDate>
        <EnteredBy>adlerm2</EnteredBy>
        <Comment>Revised term; AJCC</Comment>
       </ProcessingStatus>
       <ProcessingStatus>
        <ProcessingStatusValue>Audio re-recording pending</ProcessingStatusValue>
        <ProcessingStatusDate>2016-02-15</ProcessingStatusDate>
        <EnteredBy>saucedol</EnteredBy>
        
       </ProcessingStatus></ProcessingStatuses></Media>