<?xml version="1.0" encoding="UTF-8"?><Media xmlns:cdr="cips.nci.nih.gov/cdr" Usage="External">
  <MediaTitle>mega-voltage linear accelerator</MediaTitle>
  <PhysicalMedia>
    <SoundData>
      <SoundType>Speech</SoundType>
      <SoundEncoding>MP3</SoundEncoding>
      <RunSeconds>5</RunSeconds>
    </SoundData>
  </PhysicalMedia>
  <MediaSource>
    <OriginalSource>
      <Creator>Vanessa Richardson, VR Voice</Creator>
      <DateCreated>2012-02-17</DateCreated>
      <SourceFilename>Week_059/44688_en.mp3</SourceFilename>
    </OriginalSource>
  </MediaSource>
  <MediaContent>
    <Categories>
      <Category>pronunciation</Category>
    </Categories>
    <ContentDescriptions>
      <ContentDescription audience="Patients" language="en">Pronunciation of dictionary term "mega-voltage linear accelerator"</ContentDescription>
    </ContentDescriptions>
  </MediaContent>
  <ProposedUse>
    <Glossary cdr:ref="CDR0000044688">mega-voltage linear accelerator;acelerador lineal de megavoltaje [es]</Glossary>
  </ProposedUse>
</Media>
