<?xml version="1.0" encoding="UTF-8"?><Media xmlns:cdr="cips.nci.nih.gov/cdr" Usage="External">
  <MediaTitle>mind-body practice</MediaTitle>
  <PhysicalMedia>
    <SoundData>
      <SoundType>Speech</SoundType>
      <SoundEncoding>MP3</SoundEncoding>
      <RunSeconds>2</RunSeconds>
    </SoundData>
  </PhysicalMedia>
  <MediaSource>
    <OriginalSource>
      <Creator>Vanessa Richardson, VR Voice</Creator>
      <DateCreated>2012-07-19</DateCreated>
      <SourceFilename>Week_081/729824_en.mp3</SourceFilename>
    </OriginalSource>
  </MediaSource>
  <MediaContent>
    <Categories>
      <Category>pronunciation</Category>
    </Categories>
    <ContentDescriptions>
      <ContentDescription audience="Patients" language="en">Pronunciation of dictionary term "mind-body practice"</ContentDescription>
    </ContentDescriptions>
  </MediaContent>
  <ProposedUse>
    <Glossary cdr:ref="CDR0000729824">mind-body practice;ejercicio físicomental [es]</Glossary>
  </ProposedUse>
</Media>
