<?xml version="1.0" encoding="UTF-8"?><Media xmlns:cdr="cips.nci.nih.gov/cdr" Usage="External">
 
 <MediaTitle>testis-Spanish</MediaTitle>
  <PhysicalMedia>
    <SoundData>
      <SoundType>Speech</SoundType>
      <SoundEncoding>MP3</SoundEncoding>
      <RunSeconds>1</RunSeconds>
    </SoundData>
  </PhysicalMedia>
  <MediaSource>
    <OriginalSource>
      <Creator>Vanessa Richardson, VR Voice</Creator>
      <DateCreated>2017-10-24</DateCreated>
      <SourceFilename>367406_es.mp3</SourceFilename>
    </OriginalSource>
  </MediaSource>
  <MediaContent>
    <Categories>
      <Category>pronunciation</Category>
    </Categories>
    <ContentDescriptions>
      <ContentDescription audience="Patients" language="en">Pronunciation of dictionary term "teste"</ContentDescription>
    </ContentDescriptions>
  </MediaContent>
  <ProposedUse>
    <Glossary cdr:ref="CDR0000367406">testis</Glossary>
  </ProposedUse>
<ProcessingStatuses>
       <ProcessingStatus>
        <ProcessingStatusValue>Audio approved</ProcessingStatusValue>
        <ProcessingStatusDate>2017-10-24</ProcessingStatusDate>
        <EnteredBy>saucedol</EnteredBy>
        <Comment>Linked new audio</Comment>
       </ProcessingStatus></ProcessingStatuses></Media>
