<Media xmlns:cdr="cips.nci.nih.gov/cdr" Usage="External">
  <MediaTitle>cancer susceptibility gene mutation</MediaTitle>
  <PhysicalMedia>
    <SoundData>
      <SoundType>Speech</SoundType>
      <SoundEncoding>MP3</SoundEncoding>
      <RunSeconds>4</RunSeconds>
    </SoundData>
  </PhysicalMedia>
  <MediaSource>
    <OriginalSource>
      <Creator>Vanessa Richardson, VR Voice</Creator>
      <DateCreated>2019-02-22</DateCreated>
      <SourceFilename>Week_130/794887_en.mp3</SourceFilename>
    </OriginalSource>
  </MediaSource>
  <MediaContent>
    <Categories>
      <Category>pronunciation</Category>
    </Categories>
    <ContentDescriptions>
      <ContentDescription audience="Patients" language="en">Pronunciation of dictionary term "cancer susceptibility gene mutation"</ContentDescription>
    </ContentDescriptions>
  </MediaContent>
  <ProposedUse>
    <Glossary cdr:ref="CDR0000794887">cancer susceptibility gene mutation;mutación en gen de susceptibilidad al cáncer [es]</Glossary>
  </ProposedUse>
</Media>