<Media xmlns:cdr="cips.nci.nih.gov/cdr" BlockedFromVOL="Yes"> 
 <MediaTitle>Childhood Melanoma – Incidence Rates</MediaTitle>
 <PhysicalMedia>
  <ImageData>
   <ImageType>chart</ImageType>
   <ImageEncoding>JPEG</ImageEncoding>
   <Color>Color</Color>
   <Labeled>Yes</Labeled>
   <LabelName language="en">Rate per 1,000,000</LabelName><LabelName language="en">0</LabelName><LabelName language="en">5.0</LabelName><LabelName language="en">10</LabelName><LabelName language="en">15</LabelName><LabelName language="en">20</LabelName><LabelName language="en">25</LabelName><LabelName language="en">Legend (Sex)</LabelName><LabelName language="en">Both Sexes</LabelName><LabelName language="en">Female</LabelName><LabelName language="en">Male</LabelName><LabelName language="en">Age at Diagnosis</LabelName><LabelName language="en">&lt;1</LabelName><LabelName language="en">1</LabelName><LabelName language="en">2</LabelName><LabelName language="en">3</LabelName><LabelName language="en">4</LabelName><LabelName language="en">5</LabelName><LabelName language="en">6</LabelName><LabelName language="en">7</LabelName><LabelName language="en">8</LabelName><LabelName language="en">9</LabelName><LabelName language="en">10</LabelName><LabelName language="en">11</LabelName><LabelName language="en">12</LabelName><LabelName language="en">13</LabelName><LabelName language="en">14</LabelName><LabelName language="en">15</LabelName><LabelName language="en">16</LabelName><LabelName language="en">17</LabelName><LabelName language="en">18</LabelName><LabelName language="en">19</LabelName><ImageDimensions>
    <HeightPixels>1275</HeightPixels><WidthPixels>1950</WidthPixels></ImageDimensions>
  </ImageData>
 </PhysicalMedia>
 <MediaSource>
  <OriginalSource>
   <Creator>NCI National Childhood Cancer Registry (NCCR)</Creator>
   <DateCreated>2023-10-04</DateCreated>
   <SourceFilename>NCCR Melanoma Incidence 9-14-23 English1.jpg</SourceFilename>
  <Comment user="kuhlmanna" date="2023-10-04" audience="Internal">Terese recreated a higher resolution graph</Comment><Comment user="kuhlmanna" date="2023-09-14" audience="Internal">Copyright permission not needed</Comment></OriginalSource>
 </MediaSource>
 
 <MediaContent>
  <Categories>
   <Category>measurement</Category>
  </Categories>
  <Diagnoses>
   <Diagnosis cdr:ref="CDR0000038833">melanoma</Diagnosis>
  </Diagnoses>
  
  <ContentDescriptions>
   <ContentDescription audience="Health_professionals" language="en">Graph showing the incidence rates of melanoma from 2016 to 2020, according to age at diagnosis. The incidence rates in males, females, and both sexes are shown.</ContentDescription>
  </ContentDescriptions>
  <Captions>
   <MediaCaption audience="Health_professionals" language="en">Melanoma incidence rates by age at diagnosis from 2016 to 2020. Reprinted with permission from the National Childhood Cancer Registry. NCCR*Explorer: An interactive website for NCCR cancer statistics [Internet]. National Cancer Institute; 2023 Sep 7. [updated: 2023 Sep 8; cited 2023 Oct 4]. Available from: <ExternalRef cdr:xref="https://nccrexplorer.ccdi.cancer.gov" SourceTitle="National Childhood Cancer Registry Explorer (NCCR*Explorer)">https://nccrexplorer.ccdi.cancer.gov</ExternalRef>.</MediaCaption>
  </Captions>
 </MediaContent>
 <ProposedUse>
  <Summary cdr:ref="CDR0000800109">Childhood Melanoma Treatment</Summary>
  
 </ProposedUse>
 
<ProcessingStatuses><ProcessingStatus>
        <ProcessingStatusValue>Processing Complete</ProcessingStatusValue>
        <ProcessingStatusDate>2023-10-04</ProcessingStatusDate>
        <EnteredBy>kuhlmanna</EnteredBy>
        
       </ProcessingStatus><ProcessingStatus>
        <ProcessingStatusValue>Ready for Publishing</ProcessingStatusValue>
        <ProcessingStatusDate>2023-10-04</ProcessingStatusDate>
        <EnteredBy>kuhlmanna</EnteredBy>
        
       </ProcessingStatus>
       <ProcessingStatus>
        <ProcessingStatusValue>HP illustration approved</ProcessingStatusValue>
        <ProcessingStatusDate>2023-09-14</ProcessingStatusDate>
        <EnteredBy>kuhlmanna</EnteredBy>
        
       </ProcessingStatus></ProcessingStatuses></Media>