<Media xmlns:cdr="cips.nci.nih.gov/cdr" Usage="External">
  <MediaTitle>selective estrogen receptor degrader-Spanish</MediaTitle>
  <PhysicalMedia>
    <SoundData>
      <SoundType>Speech</SoundType>
      <SoundEncoding>MP3</SoundEncoding>
      <RunSeconds>4</RunSeconds>
    </SoundData>
  </PhysicalMedia>
  <MediaSource>
    <OriginalSource>
      <Creator>Vanessa Richardson, VR Voice</Creator>
      <DateCreated>2023-08-21</DateCreated>
      <SourceFilename>Week_2023_33/811793_es.mp3</SourceFilename>
    </OriginalSource>
  </MediaSource>
  <MediaContent>
    <Categories>
      <Category>pronunciation</Category>
    </Categories>
    <ContentDescriptions>
      <ContentDescription audience="Patients" language="es">Pronunciation of dictionary term "degradador selectivo del receptor de estrógeno"</ContentDescription>
    </ContentDescriptions>
  </MediaContent>
  <ProposedUse>
    <Glossary cdr:ref="CDR0000811793">selective estrogen receptor degrader;degradador selectivo del receptor de estrógeno regulador selectivo del receptor de estrógeno regulador negativo del receptor de estrógeno regulador por disminución selectivo de los receptores de estrógeno [es]</Glossary>
  </ProposedUse>
</Media>